IntroductionToEecsIiDigitalCommunicationSystemsMit602/README.md
IntroductionToEecsIiDigitalCommunicationSystemsMit602/__init__.py
IntroductionToEecsIiDigitalCommunicationSystemsMit602/__main__.py
IntroductionToEecsIiDigitalCommunicationSystemsMit602/file.pdf
IntroductionToEecsIiDigitalCommunicationSystemsMit602/index.html
introduction_to_eecs_ii_digital_communication_systems_mit_6_02-2024.3.2.0.dist-info/METADATA
introduction_to_eecs_ii_digital_communication_systems_mit_6_02-2024.3.2.0.dist-info/WHEEL
introduction_to_eecs_ii_digital_communication_systems_mit_6_02-2024.3.2.0.dist-info/entry_points.txt
introduction_to_eecs_ii_digital_communication_systems_mit_6_02-2024.3.2.0.dist-info/top_level.txt
introduction_to_eecs_ii_digital_communication_systems_mit_6_02-2024.3.2.0.dist-info/RECORD
